lesscode_db/__init__.py
lesscode_db/connect_pool.py
lesscode_db/connection_info.py
lesscode_db/db_options.py
lesscode_db/db_request.py
lesscode_db/ds_helper.py
lesscode_db/dynamic_import_package.py
lesscode_db/mongo_base_model.py
lesscode_db/version.py
lesscode_db-0.0.0.dist-info/LICENSE
lesscode_db-0.0.0.dist-info/METADATA
lesscode_db-0.0.0.dist-info/WHEEL
lesscode_db-0.0.0.dist-info/top_level.txt
lesscode_db-0.0.0.dist-info/RECORD
