Metadata-Version: 2.1
Name: lesscode-db
Version: 0.0.0
Summary: lesscode_db是数据库连接工具包
Author: Chao.yy
Author-email: yuyc@ishangqi.com
Maintainer: navysummer
Maintainer-email: mnavysummer@yeah.net
Platform: python
Classifier: Programming Language :: Python :: 3
Classifier: Operating System :: OS Independent
Requires-Python: >=3.6
License-File: LICENSE
